tessitura/__init__.py
tessitura-0.0.6.dist-info/LICENSE
tessitura-0.0.6.dist-info/METADATA
tessitura-0.0.6.dist-info/WHEEL
tessitura-0.0.6.dist-info/top_level.txt
tessitura-0.0.6.dist-info/RECORD
