Metadata-Version: 2.1
Name: tessitura
Version: 0.0.6
Summary: Tools for talking to the Tessitura API
Home-page: https://github.com/micahwalter/tessitura-tools
Author: Micah Walter
Author-email: micah@micahwalter.com
License: UNKNOWN
Platform: UNKNOWN
Classifier: Programming Language :: Python :: 3
Classifier: License :: OSI Approved :: MIT License
Classifier: Operating System :: OS Independent
Requires-Dist: requests
